{
  "market": "US",
  "updated": "2024-01",
  "phones": [
    {
      "id": "iphone-15-pro",
      "brand": "Apple",
      "model": "iPhone 15 Pro",
      "os": "iOS",
      "releaseYear": 2023,
      "availability": ["new", "used"],
      "price": { "new": 999, "used": 850 },
      "screen": { "sizeIn": 6.1, "class": "medium" },
      "traits": {
        "performance": 95,
        "camera": 92,
        "battery": 80,
        "value": 70,
        "reliability": 95,
        "build": 95,
        "display": 92,
        "software": 95,
        "safety": 92,
        "design": 88
      },
      "strengthTags": ["Top-tier performance", "Excellent camera", "Strong long-term reliability"]
    },
    {
      "id": "iphone-15",
      "brand": "Apple",
      "model": "iPhone 15",
      "os": "iOS",
      "releaseYear": 2023,
      "availability": ["new", "used"],
      "price": { "new": 799, "used": 680 },
      "screen": { "sizeIn": 6.1, "class": "medium" },
      "traits": {
        "performance": 88,
        "camera": 85,
        "battery": 82,
        "value": 78,
        "reliability": 93,
        "build": 90,
        "display": 88,
        "software": 95,
        "safety": 90,
        "design": 86
      },
      "strengthTags": ["Balanced iPhone value", "Strong resale & support", "Great everyday camera"]
    },
    {
      "id": "samsung-s24-ultra",
      "brand": "Samsung",
      "model": "Galaxy S24 Ultra",
      "os": "Android",
      "releaseYear": 2024,
      "availability": ["new", "used"],
      "price": { "new": 1199, "used": 950 },
      "screen": { "sizeIn": 6.8, "class": "large" },
      "traits": {
        "performance": 96,
        "camera": 94,
        "battery": 88,
        "value": 72,
        "reliability": 88,
        "build": 93,
        "display": 98,
        "software": 85,
        "safety": 92,
        "design": 85
      },
      "strengthTags": ["Best-in-class display", "Excellent zoom camera", "Top-end performance"]
    },
    {
      "id": "samsung-s24",
      "brand": "Samsung",
      "model": "Galaxy S24",
      "os": "Android",
      "releaseYear": 2024,
      "availability": ["new", "used"],
      "price": { "new": 799, "used": 650 },
      "screen": { "sizeIn": 6.2, "class": "medium" },
      "traits": {
        "performance": 90,
        "camera": 86,
        "battery": 80,
        "value": 80,
        "reliability": 86,
        "build": 88,
        "display": 90,
        "software": 85,
        "safety": 88,
        "design": 84
      },
      "strengthTags": ["Compact flagship", "Great display", "Strong all-around option"]
    },
    {
      "id": "pixel-8-pro",
      "brand": "Google",
      "model": "Pixel 8 Pro",
      "os": "Android",
      "releaseYear": 2023,
      "availability": ["new", "used"],
      "price": { "new": 999, "used": 750 },
      "screen": { "sizeIn": 6.7, "class": "large" },
      "traits": {
        "performance": 85,
        "camera": 96,
        "battery": 78,
        "value": 82,
        "reliability": 82,
        "build": 85,
        "display": 92,
        "software": 98,
        "safety": 90,
        "design": 82
      },
      "strengthTags": ["Best photography", "Fast updates", "Excellent software experience"]
    },
    {
      "id": "pixel-8",
      "brand": "Google",
      "model": "Pixel 8",
      "os": "Android",
      "releaseYear": 2023,
      "availability": ["new", "used"],
      "price": { "new": 699, "used": 550 },
      "screen": { "sizeIn": 6.2, "class": "medium" },
      "traits": {
        "performance": 82,
        "camera": 92,
        "battery": 75,
        "value": 88,
        "reliability": 80,
        "build": 82,
        "display": 88,
        "software": 98,
        "safety": 88,
        "design": 82
      },
      "strengthTags": ["Great camera for size", "Strong value", "Long update runway"]
    },
    {
      "id": "oneplus-12",
      "brand": "OnePlus",
      "model": "OnePlus 12",
      "os": "Android",
      "releaseYear": 2024,
      "availability": ["new", "used"],
      "price": { "new": 799, "used": 600 },
      "screen": { "sizeIn": 6.8, "class": "large" },
      "traits": {
        "performance": 93,
        "camera": 82,
        "battery": 90,
        "value": 85,
        "reliability": 78,
        "build": 85,
        "display": 90,
        "software": 80,
        "safety": 85,
        "design": 86
      },
      "strengthTags": ["Fast charging & battery", "High performance", "Strong value flagship"]
    },
    {
      "id": "iphone-14-pro",
      "brand": "Apple",
      "model": "iPhone 14 Pro",
      "os": "iOS",
      "releaseYear": 2022,
      "availability": ["new", "used"],
      "price": { "new": 899, "used": 700 },
      "screen": { "sizeIn": 6.1, "class": "medium" },
      "traits": {
        "performance": 90,
        "camera": 88,
        "battery": 78,
        "value": 75,
        "reliability": 94,
        "build": 93,
        "display": 90,
        "software": 94,
        "safety": 90,
        "design": 84
      },
      "strengthTags": ["Strong used Pro value", "Great camera", "Long iOS support"]
    },
    {
      "id": "iphone-se-2022",
      "brand": "Apple",
      "model": "iPhone SE (2022)",
      "os": "iOS",
      "releaseYear": 2022,
      "availability": ["new", "used"],
      "price": { "new": 429, "used": 300 },
      "screen": { "sizeIn": 4.7, "class": "small" },
      "traits": {
        "performance": 80,
        "camera": 65,
        "battery": 60,
        "value": 92,
        "reliability": 90,
        "build": 75,
        "display": 60,
        "software": 95,
        "safety": 82,
        "design": 70
      },
      "strengthTags": ["Lowest-cost iPhone", "Long software support", "Small and easy to handle"]
    },
    {
      "id": "samsung-a54",
      "brand": "Samsung",
      "model": "Galaxy A54",
      "os": "Android",
      "releaseYear": 2023,
      "availability": ["new", "used"],
      "price": { "new": 449, "used": 330 },
      "screen": { "sizeIn": 6.4, "class": "medium" },
      "traits": {
        "performance": 70,
        "camera": 75,
        "battery": 85,
        "value": 90,
        "reliability": 80,
        "build": 75,
        "display": 82,
        "software": 82,
        "safety": 84,
        "design": 78
      },
      "strengthTags": ["Great midrange value", "Strong battery", "Good screen for price"]
    }
  ]
}
